monkey/__init__.py
monkey/crawler/__init__.py
monkey/crawler/ldap/__init__.py
monkey/crawler/ldap/ldap3.py
monkey/crawler/ldap/handlers/__init__.py
monkey/crawler/ldap/handlers/ad.py
monkey.crawler.ldap-2.0.0.dev1.dist-info/LICENSE.txt
monkey.crawler.ldap-2.0.0.dev1.dist-info/METADATA
monkey.crawler.ldap-2.0.0.dev1.dist-info/WHEEL
monkey.crawler.ldap-2.0.0.dev1.dist-info/top_level.txt
monkey.crawler.ldap-2.0.0.dev1.dist-info/RECORD
