Metadata-Version: 2.1
Name: monkey.crawler.ldap
Version: 2.0.0.dev1
Summary: Monkey crawler implementation for LDAP directory.
Home-page: https://bitbucket.org/monkey-python/monkey-crawler-ldap/
Author: Xavier ROY
Author-email: xavier@regbuddy.eu
License: Apache License, Version 2.0
Platform: UNKNOWN
Classifier: Programming Language :: Python
Classifier: Development Status :: 1 - Planning
Classifier: Operating System :: OS Independent
Classifier: Programming Language :: Python :: 3.8
Classifier: Topic :: Software Development :: Libraries :: Python Modules
Classifier: Intended Audience :: Developers
License-File: LICENSE.txt
Requires-Dist: monkey.crawler (>=2.0.0.dev1)
Requires-Dist: ldap3 (>=2.9)
